MANIFEST.in
README.md
setup.py
slurmpy/__init__.py
slurmpy/slurmpy.py
slurmpy.egg-info/PKG-INFO
slurmpy.egg-info/SOURCES.txt
slurmpy.egg-info/dependency_links.txt
slurmpy.egg-info/top_level.txt