Metadata-Version: 1.1
Name: slurmpy
Version: 0.0.5
Summary: submit jobs to slurm with python
Home-page: https://github.com/brentp/slurmpy
Author: Brent Pedersen
Author-email: bpederse@gmail.com
License: MIT
Keywords: cluster slurmpy
Platform: UNKNOWN
Classifier: Development Status :: 3 - Alpha
Classifier: Topic :: Utilities
Classifier: License :: OSI Approved :: MIT License
Classifier: Programming Language :: Python :: 2
Classifier: Programming Language :: Python :: 3
